qpop/__init__.py
qpop/runner.py
qpop-1.5.dist-info/METADATA
qpop-1.5.dist-info/WHEEL
qpop-1.5.dist-info/entry_points.txt
qpop-1.5.dist-info/top_level.txt
qpop-1.5.dist-info/RECORD
